ssh_cmd/__init__.py
ssh_cmd/version.py
ssh_cmd/infrastructure/__init__.py
ssh_cmd/infrastructure/ao.py
ssh_cmd/infrastructure/do.py
ssh_command-0.0.4.dist-info/METADATA
ssh_command-0.0.4.dist-info/WHEEL
ssh_command-0.0.4.dist-info/top_level.txt
ssh_command-0.0.4.dist-info/RECORD
